setup.py
botocore_tornado/__init__.py
botocore_tornado/endpoint.py
botocore_tornado/operation.py
botocore_tornado/service.py
botocore_tornado/session.py
botocore_tornado.egg-info/PKG-INFO
botocore_tornado.egg-info/SOURCES.txt
botocore_tornado.egg-info/dependency_links.txt
botocore_tornado.egg-info/requires.txt
botocore_tornado.egg-info/top_level.txt