Metadata-Version: 1.1
Name: botocore-tornado
Version: 0.93.0
Summary: botocore subclasses that uses AsyncHTTPClient
Home-page: https://github.com/qudos-com/botocore-tornado
Author: Simon Hewitt
Author-email: simon@qudos.com.com
License: The MIT License (MIT)
